nanoretrotect
