Metadata-Version: 1.2
Name: nanoretrotect
Version: 0.3.0
Summary: UNKNOWN
Home-page: https://github.com/wdecoster/nanoretrotect
Author: Wouter De Coster
Author-email: decosterwouter@gmail.com
License: MIT
Platform: UNKNOWN
Classifier: Development Status :: 4 - Beta
Classifier: Intended Audience :: Science/Research
Classifier: Topic :: Scientific/Engineering :: Bio-Informatics
Classifier: License :: OSI Approved :: MIT License
Classifier: Programming Language :: Python :: 3
Classifier: Programming Language :: Python :: 3.3
Classifier: Programming Language :: Python :: 3.4
Classifier: Programming Language :: Python :: 3.5
Requires-Python: >=3
